fifo_buffer/fifo_buffer/fifo_buffer.srcs/sources_1/new/fifo_buffer.v
`timescale 1ns / 1ps
//////////////////////////////////////////////////////////////////////////////////
// Company: 
// Engineer: 
// 
// Create Date: 03/22/2025 10:54:24 AM
// Design Name: 
// Module Name: fifo_buffer
// Project Name: 
// Target Devices: 
// Tool Versions: 
// Description: 
// 
// Dependencies: 
// 
// Revision:
// Revision 0.01 - File Created
// Additional Comments:
// 
//////////////////////////////////////////////////////////////////////////////////


module fifo_buffer#(
    parameter BUFFER_DEPTH = 32, BUFFER_WIDTH = 4, OUTPUT_SIZE = 4
    // depth dictates amount of slots, width dictates amount of bits per slot. 
    // equate buffer width to the size of the input bus -> each time it writes, one line is added
    // output size is the amount of bits that is read at once. should be a multiple of the buffer width
    // 
    )(
    
    input clk, rst, w_en, r_en,
    input [BUFFER_WIDTH-1:0] data_in,
    output reg [OUTPUT_SIZE-1:0] data_out,
    output full, empty
    
    );
    
    reg [$clog2(BUFFER_DEPTH)-1:0] w_ptr, r_ptr, count;
    reg [BUFFER_WIDTH-1:0] fifo[BUFFER_DEPTH-1:0];
    
    localparam read_depth = $floor(OUTPUT_SIZE/BUFFER_WIDTH);
        
    always @(posedge clk) begin
    
        //general reset logic
        if (rst) begin
          w_ptr <= 0; 
          r_ptr <= 0;
          data_out <= 0;
          count <= 0;
          
        end else begin
          case({w_en,r_en})
            2'b00, 2'b11: count <= count;
            2'b01: count <= count - read_depth;
            2'b10: count <= count + 1'b1;
          endcase
        end
    end
    
    
  // To write data to FIFO
  always@(posedge clk) begin
    if(w_en & !full)begin
      fifo[w_ptr] <= data_in;
      w_ptr <= w_ptr + 1;
    end
  end
  
  // To read data from FIFO
  // 
      integer i;

  always@(posedge clk) begin
  
    if(r_en & !empty ) begin
    
        for(i=0; i < read_depth; i = i+1) begin
            data_out[BUFFER_WIDTH*i +: BUFFER_WIDTH] <= fifo[r_ptr + i];
        end

        r_ptr <= r_ptr + read_depth;
      
    end
    
  end
  
  assign full = (count == BUFFER_DEPTH);
  assign empty = (count == 0);
    
endmodule

fifo_buffer/fifo_buffer/fifo_buffer.srcs/sim_1/new/fifo_buffer_tb.v
`timescale 1ns / 1ps

module fifo_buffer_tb#(
        parameter BUFFER_DEPTH = 32, BUFFER_WIDTH = 4, OUTPUT_SIZE = 4
    )(
       output reg clk, rst, w_en, r_en,
       reg [BUFFER_WIDTH-1:0] data_in,
       wire empty, full,
       wire [OUTPUT_SIZE-1:0] data_out
    );
    
    fifo_buffer #(
            .BUFFER_DEPTH(32),
            .BUFFER_WIDTH(4),
            .OUTPUT_SIZE(16)
//        BUFFER_DEPTH, BUFFER_WIDTH, OUTPUT_SIZE
        )fifo_inst (
            .clk(clk),
            .rst(rst),
            .w_en(w_en),
            .r_en(r_en),
            .data_in(data_in),
            .data_out(data_out),
            .full(full),
            .empty(empty)
//        clk, rst, w_en, r_en, data_in, data_out, full, empty
        );


    always #2 clk = ~clk;
    
    initial begin
        clk = 0; 
        rst = 0;
        w_en = 0; 
        r_en = 0;
        data_in = 0;
        #10 rst = 1;
        #10 rst = 0;
        #10
//        drive(20);
//        drive(40);
        w_en = 1;
        data_in = $random;
        #10
        data_in = $random;
        #10
        w_en = 0;
        #10
        w_en = 0;
        data_in = $random;
        #10
        r_en = 1;
        #10
        r_en = 0
        w_en = 0;
        #19
        $finish;
      end
      
      
      
      
//      task push();
//        if(!full) begin
//          w_en = 1;
//          data_in = $random;
//          #1 $display("Push In: w_en=%b, r_en=%b, data_in=%h",w_en, r_en,data_in);
//        end
//        else begin 
//            $display("FIFO Full!! Can not push data_in=%d", data_in);
//        end 
//      endtask 
      
//      task pop();
//        if(!empty) begin
//          r_en = 1;
//          #1 $display("Pop Out: w_en=%b, r_en=%b, data_out=%h",w_en, r_en,data_out);
//        end
//        else begin 
//            $display("FIFO Empty!! Can not pop data_out");
//        end
//      endtask
      
//      task drive(integer delay);
//        w_en = 0; r_en = 0;
//        fork
//          begin
//            repeat(10) begin @(posedge clk) push(); end
//            w_en = 0;
//          end
//          begin
//            #delay;
//            repeat(10) begin @(posedge clk) pop(); end
//            r_en = 0;
//          end
//        join  
//      endtask
      
      initial begin 
        $dumpfile("dump.vcd"); $dumpvars;
      end
    
endmodule

fifo_buffer/fifo_buffer/fifo_buffer.sim/sim_1/behav/xsim/dump.vcd
$date
   Sun Mar 23 17:13:36 2025
$end

$version
  2024.2.0
  $dumpfile ("dump.vcd") 
$end

$timescale
  1ps
$end

$scope module fifo_buffer_tb $end
$var reg 1 ! clk $end
$var reg 1 " rst $end
$var reg 1 # w_en $end
$var reg 1 $ r_en $end
$var reg 4 % data_in [3:0] $end
$var wire 1 & empty $end
$var wire 1 ' full $end
$var wire 4 ( data_out [3:0] $end
$scope module fifo_inst $end
$var wire 1 ! clk $end
$var wire 1 " rst $end
$var wire 1 # w_en $end
$var wire 1 $ r_en $end
$var wire 4 % data_in [3:0] $end
$var reg 16 ) data_out [15:0] $end
$var wire 1 ' full $end
$var wire 1 & empty $end
$var reg 5 * w_ptr [4:0] $end
$var reg 5 + r_ptr [4:0] $end
$var reg 5 , count [4:0] $end
$var integer 32 - i [31:0] $end
$upscope $end
$upscope $end
$enddefinitions $end

#0
$dumpvars
0!
0"
0#
0$
b0 %
x&
0'
bx (
bx )
bx *
bx +
bx ,
bx -
$end

#2000
1!

#4000
0!

#6000
1!

#8000
0!

#10000
1!
1"
1&
b0 (
b0 )
b0 *
b0 +
b0 ,

#12000
0!

#14000
1!

#16000
0!

#18000
1!

#20000
0!
0"

#22000
1!

#24000
0!

#26000
1!

#28000
0!

#30000
1!
1#
b100 %
0&
b1 *
b1 ,

#32000
0!

#34000
1!
b10 *
b10 ,

#36000
0!

#38000
1!
b11 *
b11 ,

#40000
0!
b1 %

#42000
1!
b100 *
b100 ,

#44000
0!

#46000
1!
b101 *
b101 ,

#48000
0!

#50000
1!
0#

#52000
0!

#54000
1!

#56000
0!

#58000
1!

#60000
0!

#62000
1!

#64000
0!

#66000
1!

#68000
0!

#70000
1!
1$
b100 (
b1010001000100 )
b100 +
b1 ,
b100 -

#72000
0!

#74000
1!
b1 (
bx0001 )
b1000 +
b11101 ,
b100 -

#76000
0!

#78000
1!
bx (
bx )
b1100 +
b11001 ,
b100 -

#80000
0!

#82000
1!
b10000 +
b10101 ,
b100 -

#84000
0!

#86000
1!
b10100 +
b10001 ,
b100 -

